pydialog.cpython-312-darwin.so
py_osdialog-0.1.1.dist-info/LICENSE
py_osdialog-0.1.1.dist-info/METADATA
py_osdialog-0.1.1.dist-info/WHEEL
py_osdialog-0.1.1.dist-info/top_level.txt
py_osdialog-0.1.1.dist-info/RECORD
