Metadata-Version: 2.1
Name: py-osdialog
Version: 0.1.1
Summary: Python bindings for osdialog (https://www.github.com/AndrewBelt/osdialog)
Home-page: https://github.com/takeiteasy/pydialog
Author: George Watson
Author-email: George Watson <gigolo@hotmail.co.uk>
Project-URL: Homepage, https://github.com/takeiteasy/pydialog
Project-URL: Issues, https://github.com/takeiteasy/pydialog/issues
Classifier: Programming Language :: Python :: 3
Classifier: License :: OSI Approved :: MIT License
Classifier: Operating System :: OS Independent
Requires-Python: >=3.8
License-File: LICENSE
